LICENSE
README.md
setup.py
rockeet/__init__.py
rockeet.egg-info/PKG-INFO
rockeet.egg-info/SOURCES.txt
rockeet.egg-info/dependency_links.txt
rockeet.egg-info/requires.txt
rockeet.egg-info/top_level.txt
rockeet/Audio/__init__.py
rockeet/Audio/_profile.py
rockeet/Audio/_speakers.py
rockeet/Audio/_wave.py
rockeet/File/__init__.py
rockeet/File/_delete.py
rockeet/File/_list.py
rockeet/File/_read.py
rockeet/File/_upload.py
rockeet/Image/__init__.py
rockeet/Image/_faces.py
rockeet/Image/_identify.py
rockeet/Image/_person.py
rockeet/Image/_similarity.py
rockeet/Session/__init__.py
rockeet/Video/__init__.py
rockeet/Video/_faces.py
rockeet/Video/_stream.py
rockeet/helper/__init__.py